tftp_router_flasher/__init__.py
tftp_router_flasher/_version.py
tftp_router_flasher/main.py
tftp_router_flasher-0.0.1.dist-info/licenses/LICENSE
tftp_router_flasher-0.0.1.dist-info/METADATA
tftp_router_flasher-0.0.1.dist-info/WHEEL
tftp_router_flasher-0.0.1.dist-info/entry_points.txt
tftp_router_flasher-0.0.1.dist-info/top_level.txt
tftp_router_flasher-0.0.1.dist-info/RECORD
