Metadata-Version: 2.4
Name: tftp-router-flasher
Version: 0.0.1
Summary: Firmware rescue and flashing tool for routers via TFTP
Author-email: vr-ski <166657596+vr-ski@users.noreply.github.com>
License: GPL-2.0
Project-URL: Homepage, https://vr-ski.github.io/TFTPRouterFlasher/
Project-URL: Source, https://github.com/vr-ski/TFTPRouterFlasher
Project-URL: Issues, https://github.com/vr-ski/TFTPRouterFlasher/issues
Project-URL: CI/CD, https://github.com/vr-ski/TFTPRouterFlasher/actions
Keywords: tftp,router,firmware,recovery,networking
Classifier: Development Status :: 3 - Alpha
Classifier: Programming Language :: Python :: 3
Classifier: Programming Language :: Python :: 3.11
Classifier: Programming Language :: Python :: 3.12
Classifier: Programming Language :: Python :: 3.13
Classifier: Programming Language :: Python :: 3.14
Classifier: License :: OSI Approved :: GNU General Public License v2 (GPLv2)
Classifier: Operating System :: POSIX :: Linux
Classifier: Operating System :: MacOS
Classifier: Environment :: Console
Classifier: Topic :: System :: Networking
Classifier: Topic :: System :: Boot
Classifier: Topic :: Utilities
Classifier: Intended Audience :: System Administrators
Classifier: Intended Audience :: Developers
Requires-Python: >=3.8
License-File: LICENSE
Requires-Dist: tftpy==0.8.6
Requires-Dist: psutil==7.1.2
Provides-Extra: dev
Requires-Dist: ruff>=0.10.0; extra == "dev"
Requires-Dist: mypy>=1.14.0; extra == "dev"
Requires-Dist: pre-commit>=4.0.0; extra == "dev"
Requires-Dist: build>=1.0.0; extra == "dev"
Requires-Dist: pytest>=8.0.0; extra == "dev"
Requires-Dist: pytest-cov>=5.0.0; extra == "dev"
Requires-Dist: pytest-mock>=3.14.0; extra == "dev"
Provides-Extra: security
Requires-Dist: safety>=3.2.12; extra == "security"
Requires-Dist: bandit>=1.7.8; extra == "security"
Provides-Extra: build
Requires-Dist: build>=1.3.0; extra == "build"
Requires-Dist: twine>=6.0.0; extra == "build"
Requires-Dist: wheel>=0.44.0; extra == "build"
Requires-Dist: tomli>=2.0.2; extra == "build"
Requires-Dist: setuptools-scm>=8.1.0; extra == "build"
Dynamic: license-file
